example/__init__.py
example/config.py
example/iinterfa.py
example/iter.py
example/main.py
example/otra.py
example/prueba.py
example/ulti.py
example/utils/__init__.py
example/utils/module.py
example/utils/searchmodule1/__init__.py
example/utils/searchmodule1/module.py
injector_api/__init__.py
injector_api/container.py
injector_api/dependencyError.py
injector_api/loader.py
injector_api/scopeMiddleware.py
test/__init__.py
test/test.py
test/searchModule/__init__.py
test/searchModule/searchModule1/__init__.py
test/searchModule/searchModule1/module.py
test/searchModule/searchModule2/__init__.py
test/searchModule/searchModule2/module.py
injector_api-0.7.0.dist-info/METADATA
injector_api-0.7.0.dist-info/WHEEL
injector_api-0.7.0.dist-info/top_level.txt
injector_api-0.7.0.dist-info/RECORD
