Metadata-Version: 2.1
Name: injector-api
Version: 0.7.0
Summary: Python dependency injection library for your projects or for dependency injection in Django!!
Home-page: https://github.com/EmanuelCasta/injector_api
Author: Emanuel Castañeda Cardona
Author-email: emanuel.castaneda.cardona@gmail.com
Project-URL: Documentation, https://github.com/EmanuelCasta/injector_api/blob/master/README.md
